main.py
setup.py
gym_reschdule_combination.egg-info/PKG-INFO
gym_reschdule_combination.egg-info/SOURCES.txt
gym_reschdule_combination.egg-info/dependency_links.txt
gym_reschdule_combination.egg-info/requires.txt
gym_reschdule_combination.egg-info/top_level.txt